pyroyale/__init__.py
pyroyale/_version.py
pyroyale/api_client.py
pyroyale/configuration.py
pyroyale/exceptions.py
pyroyale/rest.py
pyroyale/api/__init__.py
pyroyale/api/cards_api.py
pyroyale/api/clans_api.py
pyroyale/api/locations_api.py
pyroyale/api/players_api.py
pyroyale/api/tournaments_api.py
pyroyale/models/__init__.py
pyroyale/models/arena.py
pyroyale/models/battle_log_entry.py
pyroyale/models/battle_log_team.py
pyroyale/models/card.py
pyroyale/models/card_icon_urls.py
pyroyale/models/card_list.py
pyroyale/models/chest.py
pyroyale/models/chest_list.py
pyroyale/models/clan.py
pyroyale/models/clan_base.py
pyroyale/models/clan_member.py
pyroyale/models/clan_member_list.py
pyroyale/models/clan_ranked.py
pyroyale/models/clan_ranking_list.py
pyroyale/models/clan_search_result.py
pyroyale/models/clan_search_result_clan.py
pyroyale/models/clan_war_ranked.py
pyroyale/models/clan_wars_ranking_list.py
pyroyale/models/error.py
pyroyale/models/game_mode.py
pyroyale/models/location.py
pyroyale/models/location_list.py
pyroyale/models/player_achievement.py
pyroyale/models/player_badge.py
pyroyale/models/player_base.py
pyroyale/models/player_detail.py
pyroyale/models/player_league_statistics.py
pyroyale/models/player_ranked.py
pyroyale/models/player_ranking_list.py
pyroyale/models/river_race.py
pyroyale/models/river_race_clan.py
pyroyale/models/river_race_clan_participant.py
pyroyale/models/river_race_log.py
pyroyale/models/river_race_log_entry.py
pyroyale/models/river_race_standing.py
pyroyale/models/search_paging.py
pyroyale/models/search_paging_cursors.py
pyroyale/models/season_statistics.py
pyroyale/models/tournament.py
pyroyale/models/tournament_detail.py
pyroyale/models/tournament_player.py
pyroyale/models/tournament_search_result.py
pyroyale/models/war.py
pyroyale/models/war_clan.py
pyroyale/models/war_current.py
pyroyale/models/war_log.py
pyroyale/models/war_participant.py
pyroyale/models/war_standing.py
pyroyale/models/war_standing_clan.py
test/__init__.py
pyroyale-1.0.4.dist-info/LICENSE
pyroyale-1.0.4.dist-info/METADATA
pyroyale-1.0.4.dist-info/WHEEL
pyroyale-1.0.4.dist-info/top_level.txt
pyroyale-1.0.4.dist-info/RECORD
