Metadata-Version: 2.1
Name: pyroyale
Version: 1.0.4
Summary: Clash Royale API wrapper for Python 3
Home-page: https://github.com/AaronTraas/pyroyale
Author: Aaron Traas
Author-email: aaron@traas.org
License: LGPLv3+
Project-URL: Bug Reports, https://github.com/AaronTraas/pyroyale/issues
Project-URL: Source, https://github.com/AaronTraas/pyroyale
Keywords: Clash Royale
Platform: UNKNOWN
Classifier: Development Status :: 3 - Alpha
Classifier: Intended Audience :: Other Audience
Classifier: License :: OSI Approved :: GNU Lesser General Public License v3 or later (LGPLv3+)
Classifier: Programming Language :: Python :: 3
Requires-Dist: certifi
Requires-Dist: python-dateutil
Requires-Dist: six (>=1.10)
Requires-Dist: urllib3 (>=1.15)
